agentive/__init__.py
agentive/agent/__init__.py
agentive/agent/base.py
agentive/embeddings/__init__.py
agentive/embeddings/base.py
agentive/embeddings/openai.py
agentive/llm/__init__.py
agentive/llm/base.py
agentive/llm/openai.py
agentive/memory/__init__.py
agentive/memory/base.py
agentive/memory/local_vector.py
agentive/toolkit/__init__.py
agentive/toolkit/base.py
agentive/toolkit/local_vector.py
agentive/utils/__init__.py
agentive/utils/common.py
agentive/utils/dict_utils.py
agentive/utils/text_utils.py
agentive/utils/evaluation/__init__.py
agentive/utils/evaluation/distance.py
agentive/utils/schema/__init__.py
agentive/utils/schema/function_call.py
agentive/utils/schema/message.py
agentive/utils/storage/__init__.py
agentive/utils/storage/local_vector.py
agentive-0.0.144.dist-info/LICENSE
agentive-0.0.144.dist-info/METADATA
agentive-0.0.144.dist-info/WHEEL
agentive-0.0.144.dist-info/top_level.txt
agentive-0.0.144.dist-info/RECORD
