Metadata-Version: 2.1
Name: agentive
Version: 0.0.144
Summary: Python-based framework for building modular and extensible language agents
Author: Morningside AI
Requires-Python: >=3.6
License-File: LICENSE
Requires-Dist: requests
Requires-Dist: pandas
Requires-Dist: tenacity
Requires-Dist: openai
Requires-Dist: pydantic
Requires-Dist: tqdm
Requires-Dist: tiktoken
Requires-Dist: numpy
